{ "frames": {
   "Soldier 0.aseprite": {
    "frame": { "x": 0, "y": 0, "w": 105, "h": 74 },
    "rotated": false,
    "trimmed": true,
    "spriteSourceSize": { "x": 92, "y": 79, "w": 105, "h": 74 },
    "sourceSize": { "w": 256, "h": 256 },
    "duration": 100
   },
   "Soldier 1.aseprite": {
    "frame": { "x": 0, "y": 0, "w": 105, "h": 74 },
    "rotated": false,
    "trimmed": true,
    "spriteSourceSize": { "x": 92, "y": 79, "w": 105, "h": 74 },
    "sourceSize": { "w": 256, "h": 256 },
    "duration": 100
   },
   "Soldier 2.aseprite": {
    "frame": { "x": 105, "y": 0, "w": 105, "h": 74 },
    "rotated": false,
    "trimmed": true,
    "spriteSourceSize": { "x": 92, "y": 79, "w": 105, "h": 74 },
    "sourceSize": { "w": 256, "h": 256 },
    "duration": 100
   },
   "Soldier 3.aseprite": {
    "frame": { "x": 105, "y": 0, "w": 105, "h": 74 },
    "rotated": false,
    "trimmed": true,
    "spriteSourceSize": { "x": 92, "y": 79, "w": 105, "h": 74 },
    "sourceSize": { "w": 256, "h": 256 },
    "duration": 100
   },
   "Soldier 4.aseprite": {
    "frame": { "x": 210, "y": 0, "w": 105, "h": 74 },
    "rotated": false,
    "trimmed": true,
    "spriteSourceSize": { "x": 92, "y": 79, "w": 105, "h": 74 },
    "sourceSize": { "w": 256, "h": 256 },
    "duration": 100
   },
   "Soldier 5.aseprite": {
    "frame": { "x": 210, "y": 0, "w": 105, "h": 74 },
    "rotated": false,
    "trimmed": true,
    "spriteSourceSize": { "x": 92, "y": 79, "w": 105, "h": 74 },
    "sourceSize": { "w": 256, "h": 256 },
    "duration": 100
   },
   "Soldier 6.aseprite": {
    "frame": { "x": 315, "y": 0, "w": 105, "h": 74 },
    "rotated": false,
    "trimmed": true,
    "spriteSourceSize": { "x": 92, "y": 79, "w": 105, "h": 74 },
    "sourceSize": { "w": 256, "h": 256 },
    "duration": 100
   },
   "Soldier 7.aseprite": {
    "frame": { "x": 420, "y": 0, "w": 105, "h": 74 },
    "rotated": false,
    "trimmed": true,
    "spriteSourceSize": { "x": 92, "y": 79, "w": 105, "h": 74 },
    "sourceSize": { "w": 256, "h": 256 },
    "duration": 100
   },
   "Soldier 8.aseprite": {
    "frame": { "x": 525, "y": 0, "w": 105, "h": 74 },
    "rotated": false,
    "trimmed": true,
    "spriteSourceSize": { "x": 92, "y": 79, "w": 105, "h": 74 },
    "sourceSize": { "w": 256, "h": 256 },
    "duration": 100
   },
   "Soldier 9.aseprite": {
    "frame": { "x": 630, "y": 0, "w": 105, "h": 74 },
    "rotated": false,
    "trimmed": true,
    "spriteSourceSize": { "x": 92, "y": 79, "w": 105, "h": 74 },
    "sourceSize": { "w": 256, "h": 256 },
    "duration": 100
   },
   "Soldier 10.aseprite": {
    "frame": { "x": 0, "y": 74, "w": 105, "h": 74 },
    "rotated": false,
    "trimmed": true,
    "spriteSourceSize": { "x": 92, "y": 79, "w": 105, "h": 74 },
    "sourceSize": { "w": 256, "h": 256 },
    "duration": 100
   },
   "Soldier 11.aseprite": {
    "frame": { "x": 105, "y": 74, "w": 105, "h": 74 },
    "rotated": false,
    "trimmed": true,
    "spriteSourceSize": { "x": 92, "y": 79, "w": 105, "h": 74 },
    "sourceSize": { "w": 256, "h": 256 },
    "duration": 100
   },
   "Soldier 12.aseprite": {
    "frame": { "x": 210, "y": 74, "w": 105, "h": 74 },
    "rotated": false,
    "trimmed": true,
    "spriteSourceSize": { "x": 92, "y": 79, "w": 105, "h": 74 },
    "sourceSize": { "w": 256, "h": 256 },
    "duration": 100
   },
   "Soldier 13.aseprite": {
    "frame": { "x": 315, "y": 74, "w": 105, "h": 74 },
    "rotated": false,
    "trimmed": true,
    "spriteSourceSize": { "x": 92, "y": 79, "w": 105, "h": 74 },
    "sourceSize": { "w": 256, "h": 256 },
    "duration": 100
   },
   "Soldier 14.aseprite": {
    "frame": { "x": 0, "y": 0, "w": 105, "h": 74 },
    "rotated": false,
    "trimmed": true,
    "spriteSourceSize": { "x": 92, "y": 79, "w": 105, "h": 74 },
    "sourceSize": { "w": 256, "h": 256 },
    "duration": 100
   },
   "Soldier 15.aseprite": {
    "frame": { "x": 420, "y": 74, "w": 105, "h": 74 },
    "rotated": false,
    "trimmed": true,
    "spriteSourceSize": { "x": 92, "y": 79, "w": 105, "h": 74 },
    "sourceSize": { "w": 256, "h": 256 },
    "duration": 100
   },
   "Soldier 16.aseprite": {
    "frame": { "x": 525, "y": 74, "w": 105, "h": 74 },
    "rotated": false,
    "trimmed": true,
    "spriteSourceSize": { "x": 92, "y": 79, "w": 105, "h": 74 },
    "sourceSize": { "w": 256, "h": 256 },
    "duration": 100
   },
   "Soldier 17.aseprite": {
    "frame": { "x": 630, "y": 74, "w": 105, "h": 74 },
    "rotated": false,
    "trimmed": true,
    "spriteSourceSize": { "x": 92, "y": 79, "w": 105, "h": 74 },
    "sourceSize": { "w": 256, "h": 256 },
    "duration": 100
   },
   "Soldier 18.aseprite": {
    "frame": { "x": 0, "y": 148, "w": 105, "h": 74 },
    "rotated": false,
    "trimmed": true,
    "spriteSourceSize": { "x": 92, "y": 79, "w": 105, "h": 74 },
    "sourceSize": { "w": 256, "h": 256 },
    "duration": 100
   },
   "Soldier 19.aseprite": {
    "frame": { "x": 105, "y": 148, "w": 105, "h": 74 },
    "rotated": false,
    "trimmed": true,
    "spriteSourceSize": { "x": 92, "y": 79, "w": 105, "h": 74 },
    "sourceSize": { "w": 256, "h": 256 },
    "duration": 100
   },
   "Soldier 20.aseprite": {
    "frame": { "x": 0, "y": 0, "w": 105, "h": 74 },
    "rotated": false,
    "trimmed": true,
    "spriteSourceSize": { "x": 92, "y": 79, "w": 105, "h": 74 },
    "sourceSize": { "w": 256, "h": 256 },
    "duration": 100
   },
   "Soldier 21.aseprite": {
    "frame": { "x": 210, "y": 148, "w": 105, "h": 74 },
    "rotated": false,
    "trimmed": true,
    "spriteSourceSize": { "x": 92, "y": 79, "w": 105, "h": 74 },
    "sourceSize": { "w": 256, "h": 256 },
    "duration": 100
   },
   "Soldier 22.aseprite": {
    "frame": { "x": 315, "y": 148, "w": 105, "h": 74 },
    "rotated": false,
    "trimmed": true,
    "spriteSourceSize": { "x": 92, "y": 79, "w": 105, "h": 74 },
    "sourceSize": { "w": 256, "h": 256 },
    "duration": 100
   },
   "Soldier 23.aseprite": {
    "frame": { "x": 420, "y": 148, "w": 105, "h": 74 },
    "rotated": false,
    "trimmed": true,
    "spriteSourceSize": { "x": 92, "y": 79, "w": 105, "h": 74 },
    "sourceSize": { "w": 256, "h": 256 },
    "duration": 100
   },
   "Soldier 24.aseprite": {
    "frame": { "x": 525, "y": 148, "w": 105, "h": 74 },
    "rotated": false,
    "trimmed": true,
    "spriteSourceSize": { "x": 92, "y": 79, "w": 105, "h": 74 },
    "sourceSize": { "w": 256, "h": 256 },
    "duration": 100
   },
   "Soldier 25.aseprite": {
    "frame": { "x": 630, "y": 148, "w": 105, "h": 74 },
    "rotated": false,
    "trimmed": true,
    "spriteSourceSize": { "x": 92, "y": 79, "w": 105, "h": 74 },
    "sourceSize": { "w": 256, "h": 256 },
    "duration": 100
   },
   "Soldier 26.aseprite": {
    "frame": { "x": 0, "y": 222, "w": 105, "h": 74 },
    "rotated": false,
    "trimmed": true,
    "spriteSourceSize": { "x": 92, "y": 79, "w": 105, "h": 74 },
    "sourceSize": { "w": 256, "h": 256 },
    "duration": 100
   },
   "Soldier 27.aseprite": {
    "frame": { "x": 105, "y": 222, "w": 105, "h": 74 },
    "rotated": false,
    "trimmed": true,
    "spriteSourceSize": { "x": 92, "y": 79, "w": 105, "h": 74 },
    "sourceSize": { "w": 256, "h": 256 },
    "duration": 100
   },
   "Soldier 28.aseprite": {
    "frame": { "x": 210, "y": 222, "w": 105, "h": 74 },
    "rotated": false,
    "trimmed": true,
    "spriteSourceSize": { "x": 92, "y": 79, "w": 105, "h": 74 },
    "sourceSize": { "w": 256, "h": 256 },
    "duration": 100
   },
   "Soldier 29.aseprite": {
    "frame": { "x": 315, "y": 222, "w": 105, "h": 74 },
    "rotated": false,
    "trimmed": true,
    "spriteSourceSize": { "x": 92, "y": 79, "w": 105, "h": 74 },
    "sourceSize": { "w": 256, "h": 256 },
    "duration": 100
   },
   "Soldier 30.aseprite": {
    "frame": { "x": 420, "y": 222, "w": 105, "h": 74 },
    "rotated": false,
    "trimmed": true,
    "spriteSourceSize": { "x": 92, "y": 79, "w": 105, "h": 74 },
    "sourceSize": { "w": 256, "h": 256 },
    "duration": 100
   },
   "Soldier 31.aseprite": {
    "frame": { "x": 525, "y": 222, "w": 105, "h": 74 },
    "rotated": false,
    "trimmed": true,
    "spriteSourceSize": { "x": 92, "y": 79, "w": 105, "h": 74 },
    "sourceSize": { "w": 256, "h": 256 },
    "duration": 100
   },
   "Soldier 32.aseprite": {
    "frame": { "x": 630, "y": 222, "w": 105, "h": 74 },
    "rotated": false,
    "trimmed": true,
    "spriteSourceSize": { "x": 92, "y": 79, "w": 105, "h": 74 },
    "sourceSize": { "w": 256, "h": 256 },
    "duration": 100
   },
   "Soldier 33.aseprite": {
    "frame": { "x": 0, "y": 296, "w": 105, "h": 74 },
    "rotated": false,
    "trimmed": true,
    "spriteSourceSize": { "x": 92, "y": 79, "w": 105, "h": 74 },
    "sourceSize": { "w": 256, "h": 256 },
    "duration": 100
   },
   "Soldier 34.aseprite": {
    "frame": { "x": 105, "y": 296, "w": 105, "h": 74 },
    "rotated": false,
    "trimmed": true,
    "spriteSourceSize": { "x": 92, "y": 79, "w": 105, "h": 74 },
    "sourceSize": { "w": 256, "h": 256 },
    "duration": 100
   },
   "Soldier 35.aseprite": {
    "frame": { "x": 210, "y": 296, "w": 105, "h": 74 },
    "rotated": false,
    "trimmed": true,
    "spriteSourceSize": { "x": 92, "y": 79, "w": 105, "h": 74 },
    "sourceSize": { "w": 256, "h": 256 },
    "duration": 100
   },
   "Soldier 36.aseprite": {
    "frame": { "x": 315, "y": 296, "w": 105, "h": 74 },
    "rotated": false,
    "trimmed": true,
    "spriteSourceSize": { "x": 92, "y": 79, "w": 105, "h": 74 },
    "sourceSize": { "w": 256, "h": 256 },
    "duration": 100
   },
   "Soldier 37.aseprite": {
    "frame": { "x": 420, "y": 296, "w": 105, "h": 74 },
    "rotated": false,
    "trimmed": true,
    "spriteSourceSize": { "x": 92, "y": 79, "w": 105, "h": 74 },
    "sourceSize": { "w": 256, "h": 256 },
    "duration": 100
   },
   "Soldier 38.aseprite": {
    "frame": { "x": 210, "y": 296, "w": 105, "h": 74 },
    "rotated": false,
    "trimmed": true,
    "spriteSourceSize": { "x": 92, "y": 79, "w": 105, "h": 74 },
    "sourceSize": { "w": 256, "h": 256 },
    "duration": 100
   },
   "Soldier 39.aseprite": {
    "frame": { "x": 525, "y": 296, "w": 105, "h": 74 },
    "rotated": false,
    "trimmed": true,
    "spriteSourceSize": { "x": 92, "y": 79, "w": 105, "h": 74 },
    "sourceSize": { "w": 256, "h": 256 },
    "duration": 100
   },
   "Soldier 40.aseprite": {
    "frame": { "x": 630, "y": 296, "w": 105, "h": 74 },
    "rotated": false,
    "trimmed": true,
    "spriteSourceSize": { "x": 92, "y": 79, "w": 105, "h": 74 },
    "sourceSize": { "w": 256, "h": 256 },
    "duration": 100
   },
   "Soldier 41.aseprite": {
    "frame": { "x": 0, "y": 370, "w": 105, "h": 74 },
    "rotated": false,
    "trimmed": true,
    "spriteSourceSize": { "x": 92, "y": 79, "w": 105, "h": 74 },
    "sourceSize": { "w": 256, "h": 256 },
    "duration": 100
   },
   "Soldier 42.aseprite": {
    "frame": { "x": 105, "y": 370, "w": 105, "h": 74 },
    "rotated": false,
    "trimmed": true,
    "spriteSourceSize": { "x": 92, "y": 79, "w": 105, "h": 74 },
    "sourceSize": { "w": 256, "h": 256 },
    "duration": 600
   }
 },
 "meta": {
  "app": "https://www.aseprite.org/",
  "version": "1.3.17-x64",
  "image": "Soldier.png",
  "format": "RGBA8888",
  "size": { "w": 735, "h": 444 },
  "scale": "1",
  "frameTags": [
   { "name": "Idle", "from": 0, "to": 5, "direction": "forward", "repeat": "2", "color": "#000000ff" },
   { "name": "Walk", "from": 6, "to": 13, "direction": "forward", "repeat": "2", "color": "#000000ff" },
   { "name": "Attack01", "from": 14, "to": 19, "direction": "forward", "repeat": "2", "color": "#000000ff" },
   { "name": "Attack02", "from": 20, "to": 25, "direction": "forward", "repeat": "2", "color": "#000000ff" },
   { "name": "Attack03", "from": 26, "to": 34, "direction": "forward", "repeat": "2", "color": "#000000ff" },
   { "name": "Hurt", "from": 35, "to": 38, "direction": "forward", "repeat": "2", "color": "#000000ff" },
   { "name": "Death", "from": 39, "to": 42, "direction": "forward", "repeat": "2", "color": "#000000ff" }
  ],
  "layers": [
   { "name": "shadow", "opacity": 255, "blendMode": "normal" },
   { "name": "main", "opacity": 255, "blendMode": "normal" },
   { "name": "effect", "opacity": 255, "blendMode": "normal" }
  ],
  "slices": [
  ]
 }
}
